boom.py
e620py/__init__.py
e620py/exceptions.py
e620py/handlers.py
e620py/networking.py
e620py/utils.py
E620py-1.0.0.dist-info/LICENSE
E620py-1.0.0.dist-info/METADATA
E620py-1.0.0.dist-info/WHEEL
E620py-1.0.0.dist-info/top_level.txt
E620py-1.0.0.dist-info/RECORD
