Metadata-Version: 2.1
Name: E620py
Version: 1.0.0
Summary: A python library for interacting with the e621 api
Author: mrcrabs695
Project-URL: Repository, https://github.com/mrcrabs695/E620py
Classifier: Programming Language :: Python :: 3
Classifier: Operating System :: OS Independent
Classifier: License :: OSI Approved :: MIT License
Requires-Python: >=3.10
License-File: LICENSE
Requires-Dist: httpx
